fabricconnector/__init__.py
fabricconnector/config.py
fabricconnector/exceptions.py
fabricconnector/api/__init__.py
fabricconnector/api/client.py
fabricconnector/connectors/__init__.py
fabricconnector/connectors/base.py
fabricconnector/connectors/exact_online.py
fabricconnector/connectors/exact_online_en.py
fabricconnector/connectors/exact_online_nl.py
fabricconnector/connectors/twinfield.py
fabricconnector/connectors/twinfield_nl.py
fabricconnector/core/__init__.py
fabricconnector/core/data_fetcher.py
fabricconnector/core/deleted_tracker.py
fabricconnector/core/deleted_tracker_twinfield.py
fabricconnector/core/entity_sync_tracker.py
fabricconnector/core/logger.py
fabricconnector/core/operation_logger.py
fabricconnector/core/version_check.py
fabricconnector/entities/__init__.py
fabricconnector/entities/base.py
fabricconnector/entities/exactonline/__init__.py
fabricconnector/entities/exactonline/base.py
fabricconnector/entities/exactonline/en/__init__.py
fabricconnector/entities/exactonline/en/absence_hours.py
fabricconnector/entities/exactonline/en/absence_registrations.py
fabricconnector/entities/exactonline/en/budget_amounts.py
fabricconnector/entities/exactonline/en/calendar.py
fabricconnector/entities/exactonline/en/companies.py
fabricconnector/entities/exactonline/en/cost_centers.py
fabricconnector/entities/exactonline/en/cost_types.py
fabricconnector/entities/exactonline/en/cost_units.py
fabricconnector/entities/exactonline/en/creditors.py
fabricconnector/entities/exactonline/en/creditors_outstanding.py
fabricconnector/entities/exactonline/en/currencies.py
fabricconnector/entities/exactonline/en/debtors.py
fabricconnector/entities/exactonline/en/debtors_outstanding.py
fabricconnector/entities/exactonline/en/deleted.py
fabricconnector/entities/exactonline/en/departments.py
fabricconnector/entities/exactonline/en/documents.py
fabricconnector/entities/exactonline/en/employees.py
fabricconnector/entities/exactonline/en/employment_contracts.py
fabricconnector-1.3.3.dist-info/licenses/LICENSE
fabricconnector-1.3.3.dist-info/METADATA
fabricconnector-1.3.3.dist-info/WHEEL
fabricconnector-1.3.3.dist-info/top_level.txt
fabricconnector-1.3.3.dist-info/RECORD
