Metadata-Version: 2.4
Name: fabricconnector
Version: 1.3.3
Summary: Python connector library for Microsoft Fabric notebooks that enables users to sync data from Exact Online and Twinfield to Fabric Lakehouse tables.
Home-page: https://www.powerbiconnector.nl
Author: Davista
Author-email: support@powerbiconnector.nl
License: Proprietary
Project-URL: Documentation, https://www.powerbiconnector.nl/docs
Project-URL: Power BI Connector, https://www.powerbiconnector.nl
Keywords: microsoft fabric lakehouse accounting exact-online twinfield afas connector
Platform: linux
Classifier: Development Status :: 4 - Beta
Classifier: Intended Audience :: Developers
Classifier: Intended Audience :: End Users/Desktop
Classifier: License :: Other/Proprietary License
Classifier: Topic :: Office/Business :: Financial :: Accounting
Classifier: Programming Language :: Python :: 3
Classifier: Programming Language :: Python :: 3.10
Classifier: Programming Language :: Python :: 3.11
Classifier: Operating System :: OS Independent
Classifier: Environment :: Other Environment
Classifier: Topic :: Database
Classifier: Topic :: Software Development :: Libraries :: Python Modules
Requires-Python: >=3.11
License-File: LICENSE
Requires-Dist: requests>=2.31.0
Requires-Dist: packaging>=23.0
Requires-Dist: pandas>=2.0.0
Requires-Dist: pyarrow>=12.0.0
Provides-Extra: dev
Requires-Dist: pytest>=7.0.0; extra == "dev"
Requires-Dist: pytest-cov>=4.0.0; extra == "dev"
Requires-Dist: black>=23.0.0; extra == "dev"
Requires-Dist: flake8>=6.0.0; extra == "dev"
Requires-Dist: mypy>=1.0.0; extra == "dev"
Requires-Dist: pyarmor>=8.0.0; extra == "dev"
Requires-Dist: twine>=4.0.0; extra == "dev"
Provides-Extra: spark
Requires-Dist: pyspark>=3.4.0; extra == "spark"
Requires-Dist: delta-spark>=2.4.0; extra == "spark"
Dynamic: author
Dynamic: author-email
Dynamic: classifier
Dynamic: description
Dynamic: description-content-type
Dynamic: home-page
Dynamic: keywords
Dynamic: license
Dynamic: license-file
Dynamic: platform
Dynamic: project-url
Dynamic: provides-extra
Dynamic: requires-dist
Dynamic: requires-python
Dynamic: summary
